{"frames": [

{
	"filename": "background.png",
	"frame": {"x":1,"y":1,"w":500,"h":400},
	"rotated": false,
	"trimmed": false,
	"spriteSourceSize": {"x":0,"y":0,"w":500,"h":400},
	"sourceSize": {"w":500,"h":400}
},
{
	"filename": "cloud.png",
	"frame": {"x":1,"y":403,"w":102,"h":71},
	"rotated": false,
	"trimmed": false,
	"spriteSourceSize": {"x":0,"y":0,"w":102,"h":71},
	"sourceSize": {"w":102,"h":71}
},
{
	"filename": "cross.png",
	"frame": {"x":105,"y":472,"w":5,"h":5},
	"rotated": false,
	"trimmed": false,
	"spriteSourceSize": {"x":0,"y":0,"w":5,"h":5},
	"sourceSize": {"w":5,"h":5}
},
{
	"filename": "hero.png",
	"frame": {"x":183,"y":403,"w":66,"h":99},
	"rotated": false,
	"trimmed": false,
	"spriteSourceSize": {"x":0,"y":0,"w":66,"h":99},
	"sourceSize": {"w":66,"h":99}
},
{
	"filename": "sun.png",
	"frame": {"x":105,"y":403,"w":76,"h":67},
	"rotated": false,
	"trimmed": false,
	"spriteSourceSize": {"x":0,"y":0,"w":76,"h":67},
	"sourceSize": {"w":76,"h":67}
}],
"meta": {
	"app": "http://www.codeandweb.com/texturepacker",
	"version": "1.0",
	"image": "spritesheet.png",
	"format": "RGBA8888",
	"size": {"w":502,"h":503},
	"scale": "1",
	"smartupdate": "$TexturePacker:SmartUpdate:77fede0e8bcca77c74017d6ebcbbd925:60caf8f2ebaf7814bf869bf5b845e1e8:729adc6043343cfda41c447ce8f464d6$"
}
}
